<?xml version="1.0" encoding="utf-8"?>
<granar>
	<planttype param="1" />
	<randomness param="3" />
	<stele cell_diameter="0.015" n_layers="1" layer_diameter="0.67" order="1" />
	<pericycle cell_diameter="0.015" n_layers="1" order="2" />
	<endodermis cell_diameter="0.0365853658536585" n_layers="1" order="3" />
	<cortex cell_diameter="0.0365853658536585" n_layers="10" order="4" />
	<exodermis cell_diameter="0.0365853658536585" n_layers="1" order="5" />
	<epidermis cell_diameter="0.0120731707317073" n_layers="1" order="6" />
	<xylem max_size="0.08584" n_files="12" order="1.5" ratio="1.86" />
	<phloem max_size="0.015" n_files="3" />
	<aerenchyma proportion="0.1" n_files="10" />
</granar>